{
  "cycle_id": "cycle_147_e1_section_heroes",
  "mission": "mission_adna_str_p5_m510_e1_brand_positioning",
  "session": "session_stanley_20260604T160140Z_v8_m510_e1_reskin_deploy",
  "decadal": "E1",
  "round": "r1b",
  "step": "step_3_generate_images",
  "model": "imagen-4.0-fast-generate-001",
  "aspect_ratio": "16:9",
  "output_target": "1408x792",
  "register": "ss_ghibli_pixel / tokyo_night",
  "started_at": "2026-06-04T16:14:01.739658+00:00",
  "calls": [
    {
      "section": "how",
      "round": "r1b",
      "variant": 1,
      "out_path": "site/src/assets/heroes/candidates/sec_how_r1b_v1.png",
      "prompt_chars": 1371,
      "status": "fail",
      "error": "no images returned",
      "elapsed_sec": 2.25
    },
    {
      "section": "how",
      "round": "r1b",
      "variant": 2,
      "out_path": "site/src/assets/heroes/candidates/sec_how_r1b_v2.png",
      "prompt_chars": 1371,
      "status": "fail",
      "error": "no images returned",
      "elapsed_sec": 2.65
    },
    {
      "section": "how",
      "round": "r1b",
      "variant": 3,
      "out_path": "site/src/assets/heroes/candidates/sec_how_r1b_v3.png",
      "prompt_chars": 1371,
      "status": "fail",
      "error": "no images returned",
      "elapsed_sec": 2.2
    }
  ],
  "total_cost_usd": 0.0,
  "finished_at": "2026-06-04T16:14:08.842194+00:00"
}